{"unidirectionalNeighbors": [{"id": "localhost33179", "ip": "localhost", "port": 33179, "last_heard_of": 5, "sent_to_count": 0, "recieved_from_count": 2, "availability_time": 0}, {"id": "localhost42591", "ip": "localhost", "port": 42591, "last_heard_of": 1, "sent_to_count": 0, "recieved_from_count": 0, "availability_time": 0}]}{"bidirectionalNeighbors": [{"id": "localhost59975", "ip": "localhost", "port": 59975, "last_heard_of": 2, "sent_to_count": 7, "recieved_from_count": 7, "availability_time": "12.0%"}, {"id": "localhost43825", "ip": "localhost", "port": 43825, "last_heard_of": 7, "sent_to_count": 1, "recieved_from_count": 0, "availability_time": 7}]}